list_youtube_channel/__init__.py
list_youtube_channel/get_channel.py
list_youtube_channel-2.0.2.dist-info/LICENSE
list_youtube_channel-2.0.2.dist-info/METADATA
list_youtube_channel-2.0.2.dist-info/WHEEL
list_youtube_channel-2.0.2.dist-info/top_level.txt
list_youtube_channel-2.0.2.dist-info/RECORD
