Metadata-Version: 2.1
Name: list-youtube-channel
Version: 2.0.2
Summary: Get all videos for a Youtube channel
Home-page: https://github.com/dermasmid/scrapetube
Author: Cheskel Twersky
Author-email: twerskycheskel@gmail.com
License: MIT
Keywords: youtube python channel videos list get
Platform: UNKNOWN
Classifier: Programming Language :: Python :: 3
Classifier: License :: OSI Approved :: MIT License
Classifier: Operating System :: OS Independent
Requires-Python: >=3.6
Requires-Dist: requests
